LICENSE-Kyber.rst
MANIFEST.in
README.md
pyproject.toml
setup.py
cffi_modules/kyber1024_clean.py
cffi_modules/kyber512_clean.py
cffi_modules/kyber768_clean.py
lib/PQClean/crypto_kem/kyber1024/clean/cbd.c
lib/PQClean/crypto_kem/kyber1024/clean/indcpa.c
lib/PQClean/crypto_kem/kyber1024/clean/kem.c
lib/PQClean/crypto_kem/kyber1024/clean/ntt.c
lib/PQClean/crypto_kem/kyber1024/clean/poly.c
lib/PQClean/crypto_kem/kyber1024/clean/polyvec.c
lib/PQClean/crypto_kem/kyber1024/clean/reduce.c
lib/PQClean/crypto_kem/kyber1024/clean/symmetric-shake.c
lib/PQClean/crypto_kem/kyber1024/clean/verify.c
lib/PQClean/crypto_kem/kyber1024/clean/../../../common/fips202.c
lib/PQClean/crypto_kem/kyber1024/clean/../../../common/randombytes.c
lib/PQClean/crypto_kem/kyber1024/clean/../../../common/sha2.c
lib/PQClean/crypto_kem/kyber512/clean/cbd.c
lib/PQClean/crypto_kem/kyber512/clean/indcpa.c
lib/PQClean/crypto_kem/kyber512/clean/kem.c
lib/PQClean/crypto_kem/kyber512/clean/ntt.c
lib/PQClean/crypto_kem/kyber512/clean/poly.c
lib/PQClean/crypto_kem/kyber512/clean/polyvec.c
lib/PQClean/crypto_kem/kyber512/clean/reduce.c
lib/PQClean/crypto_kem/kyber512/clean/symmetric-shake.c
lib/PQClean/crypto_kem/kyber512/clean/verify.c
lib/PQClean/crypto_kem/kyber512/clean/../../../common/fips202.c
lib/PQClean/crypto_kem/kyber512/clean/../../../common/randombytes.c
lib/PQClean/crypto_kem/kyber512/clean/../../../common/sha2.c
lib/PQClean/crypto_kem/kyber768/clean/cbd.c
lib/PQClean/crypto_kem/kyber768/clean/indcpa.c
lib/PQClean/crypto_kem/kyber768/clean/kem.c
lib/PQClean/crypto_kem/kyber768/clean/ntt.c
lib/PQClean/crypto_kem/kyber768/clean/poly.c
lib/PQClean/crypto_kem/kyber768/clean/polyvec.c
lib/PQClean/crypto_kem/kyber768/clean/reduce.c
lib/PQClean/crypto_kem/kyber768/clean/symmetric-shake.c
lib/PQClean/crypto_kem/kyber768/clean/verify.c
lib/PQClean/crypto_kem/kyber768/clean/../../../common/fips202.c
lib/PQClean/crypto_kem/kyber768/clean/../../../common/randombytes.c
src/pypqc_cffi_bindings_kyber.egg-info/PKG-INFO
src/pypqc_cffi_bindings_kyber.egg-info/SOURCES.txt
src/pypqc_cffi_bindings_kyber.egg-info/dependency_links.txt
src/pypqc_cffi_bindings_kyber.egg-info/requires.txt
src/pypqc_cffi_bindings_kyber.egg-info/top_level.txt