Metadata-Version: 2.1
Name: pypqc-cffi-bindings-kyber
Version: 0.0.1.dev0
License: NIST PQC License Summary and Excerpts
Classifier: License :: Free To Use But Restricted
Classifier: License :: Public Domain
License-File: LICENSE-Kyber.rst
Requires-Dist: cffi>=1.0.0; platform_python_implementation != "PyPy"
